{
  "name": "Мы Твоя Церковь (Ты - наш Бог)",
  "text": [
    {
      "name": "Куплет 1",
      "text": "Мы - Твоя Церковь\nИзбрана Тобой\nМы Твои дети\nПризваны все в свет Твой"
    },
    {
      "name": "Предприпев",
      "text": "Вот мы здесь, Господь\nПред Твоим лицом\nМы хотим войти\nВ славу вечности"
    },
    {
      "name": "Припев",
      "text": "Ты - наш Бог\nНе объять любовь Твою\nПоём Тебе хвалу\nПоём Тебе хвалу"
    },
    {
      "name": "Куплет 2",
      "text": "Невеста Твоя\nЕдиная в Тебе\nНесёт Твою жизнь\nИ свет любви Твоей"
    },
    {
      "name": "Мост",
      "text": "Хвала Тебе, Праведный\nХвала Тебе, Царь живых\nХвала Тебе, Ты Бог чудес\nТы - жизнь"
    }
  ],
  "chords": [
    {
      "name": "Вступление",
      "chords": "Dm | Am B♭ |"
    },
    {
      "name": "Куплет",
      "chords": "Dm | Am | B♭ | Dm |"
    },
    {
      "name": "Предприпев",
      "chords": "C | Dm | C | Dm |\nC | Dm | C | B♭ | B♭ |"
    },
    {
      "name": "Припев",
      "chords": "F | F | C | C |\nB♭ | B♭ | E♭ | E♭ | (на повтор)\n\nF | F | C | C |\nB♭ | B♭ | Dm | Dm |"
    },
    {
      "name": "Мост",
      "chords": "B♭ C | Dm C |\nB♭ C | Dm C/E |\nB♭ C | Dm C |\nB♭ | C |"
    },
    {
      "name": "Проигрыш",
      "chords": "Gm Dm | F C |\nGm Dm | F C |\nGm Dm | F C |\nB♭ | C |"
    }
  ],
  "key": "Dm"
}