{
  "name": "Только Твоему лишь Слову верю я",
  "text": [
    {
      "name": "Куплет",
      "text": "Только Твоему лишь Слову верю я\nСлово Твоё верно, истинно\nВсё что там написано это не зря\nСо Словом моя вера подросла\n\nТолько Твоему лишь Слову верим мы\nВедь оно подарено с небес\nБоже, Ты назвал Своими нас детьми\nВ Слове Иисуса сила есть"
    },
    {
      "name": "Припев",
      "text": "Я знаю, я верю\nТы Бог вечный, бесконечный\nЯ знаю, я верю \nИисус, Ты друг навечно\n\nМы знаем, мы верим\nВсемогущий, Вездесущий\nМы знаем, мы верим\nНас Господь всему научит"
    },
    {
      "name": "",
      "text": "Наш Бог\nО-о-о\nНаш Бог"
    }
  ],
  "chords": [
    {
      "name": "Куплет",
      "chords": "Dm | Gm | B♭ | C |"
    },
    {
      "name": "Припев, проигрыш",
      "chords": "Dm | B♭ | F | C |"
    }
  ],
  "text_chords": [
    {
      "name": "Куплет",
      "text_chords": "Dm                       Gm\nТолько Твоему лишь Слову верю я\n  Bb              C\nСлово Твоё верно, истинно\n Dm                   Gm\nВсё что там написано это не зря\n     Bb             C\nСо Словом моя вера подросла\n\nDm                       Gm\nТолько Твоему лишь Слову верим мы\n Bb             C\nВедь оно подарено с небес\nDm                     Gm\nБоже, Ты назвал Своими нас детьми\n    Bb          C\nВ Слове Иисуса сила есть"
    },
    {
      "name": "Припев",
      "text_chords": "Dm      Bb\nЯ знаю, я верю\n F              C\nТы Бог вечный, бесконечный\nDm      Bb\nЯ знаю, я верю \nF           C\nИисус, Ты друг навечно\n\nDm         Bb\nМы знаем, мы верим\n  F          C\nВсемогущий, Вездесущий\nDm         Bb\nМы знаем, мы верим\n F              C\nНас Господь всему научит"
    },
    {
      "name": "",
      "text_chords": "    Dm  Bb\nНаш Бог\nF   C\nО-о-о\n    Dm  Bb F  C\nНаш Бог"
    }
  ],
  "key": "Dm",
  "private": true,
  "users_read": [
    "mavrinia",
    "songs_for_kids"
  ],
  "users_write": [
    "titovtima",
    "Серж",
    "lilkatit"
  ]
}